github_bot_close_inactive_issues/__init__.py
github_bot_close_inactive_issues/close_inactive_issues.py
github_bot_close_inactive_issues/issues.py
github_bot_close_inactive_issues/logging.conf
github_bot_close_inactive_issues/rate_limit.py
github_bot_close_inactive_issues/utils.py
github_bot_close_inactive_issues-0.0.3.dist-info/DESCRIPTION.rst
github_bot_close_inactive_issues-0.0.3.dist-info/METADATA
github_bot_close_inactive_issues-0.0.3.dist-info/RECORD
github_bot_close_inactive_issues-0.0.3.dist-info/WHEEL
github_bot_close_inactive_issues-0.0.3.dist-info/entry_points.txt
github_bot_close_inactive_issues-0.0.3.dist-info/metadata.json
github_bot_close_inactive_issues-0.0.3.dist-info/top_level.txt
