Metadata-Version: 2.0
Name: github-bot-close-inactive-issues
Version: 0.0.3
Summary: Bot for automatically closing inactive issues in GitHub repositories
Home-page: https://github.com/bstriner/github-bot
Author: Ben Striner
Author-email: btriner@gmail.com
License: MIT
Download-URL: https://github.com/bstriner/github-bot-close-inactive-issues/tarball/v0.0.3
Keywords: github,issues,inactive,abandoned
Platform: UNKNOWN
Classifier: Intended Audience :: Developers
Classifier: License :: OSI Approved :: MIT License
Classifier: Programming Language :: Python :: 2
Classifier: Programming Language :: Python :: 3
Requires-Dist: PyGithub
